{
  "name": "فاندر | مركز المساعدة",
  "colors": {
    "light": {
      "brand": "#9472E4",
      "heading": "#9472E4",
      "text": "#5d5d5b"
    },
    "dark": {
      "brand": "#9472E4",
      "heading": "#9472E4",
      "text": "#efedde"
    }
  },
  "navigation": {
    "tabs": [
      {
        "tab": "مركز المعرفة",
        "icon": "book",
        "groups": [
          {
            "group": "فاندر | نبسط العالم الرقمي",
            "pages": [
              {
                "title": "الرئيسية",
                "path": "home",
                "icon": "home-icon"
              },
              {
                "title": "البداية",
                "path": "start",
                "icon": "rocket"
              }
            ]
          },
          {
            "group": "المفاهيم الأساسية",
            "pages": [
              {
                "title": "لماذا فاندر؟",
                "path": "features",
                "icon": "stars-icon"
              },
              {
                "title": "الاسئلة الشائعة",
                "path": "faqs",
                "icon": "lucide-info"
              }
            ]
          }
        ]
      },
      {
        "tab": "مركز المساعدة",
        "icon": "help-circle",
        "pages": [
          {
            "title": "مركز المساعدة",
            "path": "help-center",
            "icon": "message-circle-question"
          },
          {
            "group": "الأسئلة الشائعة",
            "icon": "help-circle",
            "expandable": false,
            "pages": [
              {
                "title": "طلب كود لعبة",
                "path": "help-center/faq/طلب-كود-لعبة"
              }
            ]
          },
          {
            "group": "حل المشاكل",
            "icon": "alert-triangle",
            "expandable": false,
            "pages": [
              {
                "title": "لم يصل الكود",
                "path": "help-center/troubleshooting/لم-يصل-الكود"
              }
            ]
          },
          {
            "group": "الإرشادات والمعلومات العامة",
            "icon": "book-open",
            "expandable": false,
            "pages": [
              {
                "title": "شراء كود",
                "path": "help-center/guides/شراء-كود"
              }
            ]
          }
        ]
      },
      {
        "tab": "سجل التغييرات",
        "icon": "clock",
        "pages": [
          {
            "title": "سجل التغييرات",
            "path": "changelog",
            "icon": "history"
          }
        ]
      }
    ]
  },
  "template": "classic",
  "logo-light": "https://blob-cdn.documentation.ai/org-db611dbb-2a6c-4ba7-ad56-fcd86de448a7/doc-af65cd44-e173-40b9-a8f2-6028b20a6784/1770897638703-xklbjp1ixjc-Logo-Square.png?q=85&fm=auto&auto=compress%2Cformat",
  "favicon": "https://blob-cdn.documentation.ai/org-db611dbb-2a6c-4ba7-ad56-fcd86de448a7/doc-af65cd44-e173-40b9-a8f2-6028b20a6784/1770897638703-xklbjp1ixjc-Logo-Square.png?q=85&fm=auto&auto=compress%2Cformat",
  "logo-dark": "https://blob-cdn.documentation.ai/org-db611dbb-2a6c-4ba7-ad56-fcd86de448a7/doc-af65cd44-e173-40b9-a8f2-6028b20a6784/1770897638703-xklbjp1ixjc-Logo-Square.png?q=85&fm=auto&auto=compress%2Cformat",
  "navbar": {
    "actions": {
      "primary": {
        "title": "المتجر الإلكتروني",
        "link": "https://vandarstore.com"
      }
    }
  }
}